systemverilog/day02_mux/dut.sv
module mux2to1 (
  input a, 
  input b,
  input sel,
  output reg y
);
  
  always @(*) begin
    case (sel)
      1'b0: y = a;
      1'b1: y = b;
      default: y = 1'b0;
    endcase
  end
endmodule

verilog/day02_mux/tb.sv
module testbench ();
  
  logic a, b, sel, y;
  
  mux2to1 dut1 (.a(a), .b(b), .sel(sel), .y(y));
  
  initial begin
    $dumpfile("dump.vcd");
    $dumpvars;
    a = 0;
    b = 0;
    sel = 0;
    
    #5;
    
    a = 0;
    b = 0;
    sel = 1;
    
    #5;
    
    a = 0;
    b = 1;
    sel = 0;
    
    #5;
    
    a = 0;
    b = 1;
    sel = 1;
    
    #5;
    
    a = 1;
    b = 0;
    sel = 0;
    
    #5;
    
    a = 1;
    b = 0;
    sel = 1;
    
    #5;
    
    a = 1;
    b = 1;
    sel = 0;
    
    #5;
    
    a = 1;
    b = 1;
    sel = 1;
    
    #5;
  end
  initial begin
    $display("Time\ta\tb\tsel\ty");
    $monitor("%0t\t%b\t%b\t%b\t%b", $time, a, b, sel, y);
  end
endmodule

verilog/day02_mux/dump.vcd
$date
	Tue Mar 10 16:43:06 2026
$end
$version
	Icarus Verilog
$end
$timescale
	1s
$end
$scope module testbench $end
$var wire 1 ! y $end
$var reg 1 " a $end
$var reg 1 # b $end
$var reg 1 $ sel $end
$scope module dut1 $end
$var wire 1 " a $end
$var wire 1 # b $end
$var wire 1 $ sel $end
$var reg 1 ! y $end
$upscope $end
$upscope $end
$enddefinitions $end
$comment Show the parameter values. $end
$dumpall
$end
#0
$dumpvars
0$
0#
0"
0!
$end
#5
1$
#10
0$
1#
#15
1!
1$
#20
0$
0#
1"
#25
0!
1$
#30
1!
0$
1#
#35
1$
